pjrt_util.py
ray_tpu.py
ray_tpu_test.py
ray_tpu_unit_test.py
ray_tpu-0.0.5.dist-info/licenses/LICENSE
ray_tpu-0.0.5.dist-info/METADATA
ray_tpu-0.0.5.dist-info/WHEEL
ray_tpu-0.0.5.dist-info/top_level.txt
ray_tpu-0.0.5.dist-info/RECORD
