Metadata-Version: 2.4
Name: ray-tpu
Version: 0.0.5
Summary: An utility for running Ray with Cloud TPUs
Author-email: Richard Liu <ricliu@google.com>, Quinn Yan <qinyiyan@google.com>
Project-URL: Homepage, https://github.com/richardsliu/ray-tpu
Project-URL: Issues, https://github.com/richardsliu/ray-tpu/issues
Classifier: Programming Language :: Python :: 3
Classifier: License :: OSI Approved :: MIT License
Classifier: Operating System :: OS Independent
Requires-Python: >=3.8
License-File: LICENSE
Dynamic: license-file
